euilee_lee-0.3.0.dist-info/METADATA
euilee_lee-0.3.0.dist-info/WHEEL
euilee_lee/__init__.py
euilee_lee/pitcher.py
euilee_lee-0.3.0.dist-info/RECORD
