Metadata-Version: 2.1
Name: euilee-lee
Version: 0.3.0
Summary: A left-handed pitcher for the KIA Tigers.
Author-Email: rim <kylttop01@gmail.com>
License: MIT
Requires-Python: >=3.7
